colab_mcp/__init__.py
colab_mcp/cli.py
colab_mcp/main.py
colab_mcp/paths.py
colab_mcp/readers.py
colab_mcp/services.py
colab_mcp/types.py
colab_mcp-0.1.0.dist-info/licenses/LICENSE
colab_mcp-0.1.0.dist-info/METADATA
colab_mcp-0.1.0.dist-info/WHEEL
colab_mcp-0.1.0.dist-info/entry_points.txt
colab_mcp-0.1.0.dist-info/top_level.txt
colab_mcp-0.1.0.dist-info/RECORD
