Metadata-Version: 2.4
Name: colab_mcp
Version: 0.1.0
Summary: Colab MCP - Local stdio MCP server to expose Claude/IDE logs as tools/resources
Requires-Python: >=3.10
License-File: LICENSE
Requires-Dist: fastmcp>=2.0.0
Requires-Dist: pydantic>=2.5.0
Requires-Dist: rich>=13.7.0
Dynamic: license-file
